BoschRpaMagicAgent/__init__.py
BoschRpaMagicAgent/common_config.py
BoschRpaMagicAgent/determine_tool_category.py
BoschRpaMagicAgent/smb_functions_manager.py
BoschRpaMagicAgent/start_agent.py
BoschRpaMagicAgent/tool_registry.py
BoschRpaMagicAgent/tools/__init__.py
BoschRpaMagicAgent/tools/download_page_clean.py
BoschRpaMagicAgent/tools/send_email_functions.py
BoschRpaMagicAgent/tools/share_driver_functions.py
boschrpamagicagent-0.0.12.dist-info/licenses/LICENSE
boschrpamagicagent-0.0.12.dist-info/METADATA
boschrpamagicagent-0.0.12.dist-info/WHEEL
boschrpamagicagent-0.0.12.dist-info/top_level.txt
boschrpamagicagent-0.0.12.dist-info/RECORD
