Metadata-Version: 2.4
Name: BoschRpaMagicAgent
Version: 0.0.12
Summary: This package is used for building automation agent functions for rpa within Bosch
Author-email: LV Zhichao <zhichao.lv@cn.bosch.com>
Project-URL: Homepage, https://github.boschdevcloud.com/LZV2SZH/BoschRpaMagicAgent
Project-URL: Bug Tracker, https://github.boschdevcloud.com/LZV2SZH/BoschRpaMagicAgent/issues
Classifier: Programming Language :: Python :: 3
Classifier: License :: OSI Approved :: MIT License
Classifier: Operating System :: OS Independent
Requires-Python: >=3.9
License-File: LICENSE
Requires-Dist: openpyxl
Requires-Dist: xlrd
Requires-Dist: smbprotocol
Requires-Dist: requests
Requires-Dist: pymysql
Requires-Dist: pandas
Requires-Dist: browser_use
Requires-Dist: langchain-core
Requires-Dist: langchain_openai
Dynamic: license-file
